ditto_lib/__init__.py
ditto_lib/book.py
ditto_lib/itemcollection.py
ditto_lib/clustering/__init__.py
ditto_lib/clustering/cluster.py
ditto_lib/clustering/clustercollection.py
ditto_lib/tasks/__init__.py
ditto_lib/tasks/calc_error.py
ditto_lib/tasks/calc_similarity.py
ditto_lib/tasks/outliers.py
ditto_lib/tasks/pca.py
ditto_lib/tasks/random_forest.py
ditto_lib/utils/__init__.py
ditto_lib/utils/checker.py
ditto_lib/utils/dataframe.py
ditto_lib/utils/error.py
ditto_lib/utils/logging.py
ditto_lib/utils/scalar.py
ditto_lib/utils/similarity.py
ditto_lib-1.0.2.dist-info/LICENSE
ditto_lib-1.0.2.dist-info/METADATA
ditto_lib-1.0.2.dist-info/WHEEL
ditto_lib-1.0.2.dist-info/top_level.txt
ditto_lib-1.0.2.dist-info/RECORD
