Metadata-Version: 2.1
Name: ditto-lib
Version: 1.0.2
Summary: Data analysis tools
Home-page: https://github.com/hgromer/ditto
Author: Hernan Gelaf-Romer
Author-email: nanug33@gmail.com
License: MIT
Platform: UNKNOWN
Requires-Dist: colorlogging
Requires-Dist: ordered-set
